shared_auth/__init__.py
shared_auth/abstract_models.py
shared_auth/app.py
shared_auth/authentication.py
shared_auth/conf.py
shared_auth/decorators.py
shared_auth/exceptions.py
shared_auth/fields.py
shared_auth/managers.py
shared_auth/middleware.py
shared_auth/mixins.py
shared_auth/models.py
shared_auth/permissions.py
shared_auth/permissions_cache.py
shared_auth/permissions_helpers.py
shared_auth/router.py
shared_auth/serializers.py
shared_auth/storage_backend.py
shared_auth/urls.py
shared_auth/utils.py
shared_auth/views.py
shared_auth/management/__init__.py
shared_auth/management/commands/__init__.py
shared_auth/management/commands/generate_permissions.py
maquinaweb_shared_auth-0.2.78.dist-info/METADATA
maquinaweb_shared_auth-0.2.78.dist-info/WHEEL
maquinaweb_shared_auth-0.2.78.dist-info/top_level.txt
maquinaweb_shared_auth-0.2.78.dist-info/RECORD
