Metadata-Version: 2.4
Name: maquinaweb-shared-auth
Version: 0.2.78
Summary: Models read-only para autenticação compartilhada entre projetos Django.
Author-email: Seu Nome <seuemail@dominio.com>
License: MIT
Project-URL: Homepage, https://github.com/maquinaweb/maquinaweb-shared-auth
Project-URL: Repository, https://github.com/maquinaweb/maquinaweb-shared-auth
Project-URL: Issues, https://github.com/maquinaweb/maquinaweb-shared-auth/issues
Keywords: django,auth,models,shared
Classifier: Framework :: Django
Classifier: Programming Language :: Python :: 3
Classifier: License :: OSI Approved :: MIT License
Classifier: Operating System :: OS Independent
Requires-Python: >=3.8
Requires-Dist: django>=5
Requires-Dist: django-storages>=1.14.6
Requires-Dist: djangorestframework>=3
Requires-Dist: pyyaml>=6.0.3
Requires-Dist: setuptools>=70
Requires-Dist: maquinaweb-shared-msg>=0.1.13
Dynamic: requires-python
